envirest/__init__.py
envipath_api-0.3.0.dist-info/LICENSE
envipath_api-0.3.0.dist-info/METADATA
envipath_api-0.3.0.dist-info/WHEEL
envipath_api-0.3.0.dist-info/top_level.txt
envipath_api-0.3.0.dist-info/RECORD
