Metadata-Version: 2.1
Name: envipath-api
Version: 0.3.0
Summary: wrapper for rest calls to envipath
Home-page: https://github.com/emanuel-schmid/envipath-api
Author: Emanuel Schmid
Author-email: schmide@ethz.ch
License: MIT
License-File: LICENSE
Requires-Dist: argparse
Requires-Dist: requests
